three_d_city_model_generator/__init__.py
three_d_city_model_generator/cli.py
three_d_city_model_generator/three_d_city_model_generator.py
three_d_city_model_generator/download/__init__.py
three_d_city_model_generator/download/gee.py
three_d_city_model_generator/download/mbfp.py
three_d_city_model_generator/download/nasadem.py
three_d_city_model_generator/download/urbanwatch.py
three_d_city_model_generator/download/utils.py
three_d_city_model_generator/geo/__init_.py
three_d_city_model_generator/geo/draw.py
three_d_city_model_generator/geo/grid.py
three_d_city_model_generator/geo/utils.py
three_d_city_model_generator/utils/__init_.py
three_d_city_model_generator/utils/envimet_inx.py
three_d_city_model_generator/utils/visualization.py
three_d_city_model_generator-0.1.4.dist-info/AUTHORS.rst
three_d_city_model_generator-0.1.4.dist-info/LICENSE
three_d_city_model_generator-0.1.4.dist-info/METADATA
three_d_city_model_generator-0.1.4.dist-info/WHEEL
three_d_city_model_generator-0.1.4.dist-info/entry_points.txt
three_d_city_model_generator-0.1.4.dist-info/top_level.txt
three_d_city_model_generator-0.1.4.dist-info/RECORD
